Metadata-Version: 1.0
Name: obvious
Version: 2.0.0
Summary: bunch of obvious functionality
Home-page: http://github.com/dansgithubuser/obvious
Author: danspypiuser
Author-email: dansonlinepresence@gmail.com
License: MIT
Platform: UNKNOWN
